[
  {
    "id": "99363348-8492-4475-96fd-066c460bb6a4",
    "data": [
      {
        "text": "just going to say hi",
        "userDefined": false
      }
    ],
    "isTemplate": false,
    "count": 0,
    "updated": 0
  },
  {
    "id": "43e60d25-9f73-4ac1-a2f1-b0127e814f3c",
    "data": [
      {
        "text": "heya",
        "userDefined": false
      }
    ],
    "isTemplate": false,
    "count": 0,
    "updated": 0
  },
  {
    "id": "fcc66155-e3c9-468c-b57f-104095b5adbb",
    "data": [
      {
        "text": "hello hi",
        "userDefined": false
      }
    ],
    "isTemplate": false,
    "count": 0,
    "updated": 0
  },
  {
    "id": "b13719e6-b430-416b-a73d-253759d32caf",
    "data": [
      {
        "text": "howdy",
        "userDefined": false
      }
    ],
    "isTemplate": false,
    "count": 0,
    "updated": 0
  },
  {
    "id": "6e06ae9b-6fd4-4c47-a81e-b6fac26e2d85",
    "data": [
      {
        "text": "hey there",
        "userDefined": false
      }
    ],
    "isTemplate": false,
    "count": 0,
    "updated": 0
  },
  {
    "id": "3e29bcad-fbf8-47fd-8ab5-1fb4ef62a4f8",
    "data": [
      {
        "text": "hi there",
        "userDefined": false
      }
    ],
    "isTemplate": false,
    "count": 0,
    "updated": 0
  },
  {
    "id": "8d39d93e-1f48-4373-9169-4610c2acded0",
    "data": [
      {
        "text": "greetings",
        "userDefined": false
      }
    ],
    "isTemplate": false,
    "count": 0,
    "updated": 0
  },
  {
    "id": "12f369f5-f332-4564-8d0f-14cdc2678b31",
    "data": [
      {
        "text": "hey",
        "userDefined": false
      }
    ],
    "isTemplate": false,
    "count": 0,
    "updated": 0
  },
  {
    "id": "8a17fae1-da73-4f86-9b08-c44358c4d7e1",
    "data": [
      {
        "text": "long time no see",
        "userDefined": false
      }
    ],
    "isTemplate": false,
    "count": 0,
    "updated": 0
  },
  {
    "id": "6df24de9-f09c-4bbc-8875-a69786488343",
    "data": [
      {
        "text": "hello",
        "userDefined": false
      }
    ],
    "isTemplate": false,
    "count": 0,
    "updated": 0
  },
  {
    "id": "a35cb28e-80f6-44bc-a188-9606590540eb",
    "data": [
      {
        "text": "lovely day isn\u0027t it",
        "userDefined": false
      }
    ],
    "isTemplate": false,
    "count": 0,
    "updated": 0
  },
  {
    "id": "ae1a81ce-c48d-42c9-b026-1f4ba204d448",
    "data": [
      {
        "text": "I greet you",
        "userDefined": false
      }
    ],
    "isTemplate": false,
    "count": 0,
    "updated": 0
  },
  {
    "id": "555449dd-8a2b-4155-95a5-208fe7175a99",
    "data": [
      {
        "text": "hello again",
        "userDefined": false
      }
    ],
    "isTemplate": false,
    "count": 0,
    "updated": 0
  },
  {
    "id": "e83bb11f-aa53-4c09-87d1-b03bed3da3da",
    "data": [
      {
        "text": "hi",
        "userDefined": false
      }
    ],
    "isTemplate": false,
    "count": 0,
    "updated": 0
  },
  {
    "id": "3272b7db-96c2-41c0-b206-5fbc5271e37a",
    "data": [
      {
        "text": "hello there",
        "userDefined": false
      }
    ],
    "isTemplate": false,
    "count": 0,
    "updated": 0
  },
  {
    "id": "36621102-852b-48bb-8318-88fcfc94d9ce",
    "data": [
      {
        "text": "hi there",
        "userDefined": false
      }
    ],
    "isTemplate": false,
    "count": 0,
    "updated": 0
  },
  {
    "id": "499e1615-16e1-40bb-b41b-ceadca343654",
    "data": [
      {
        "text": "a good day",
        "userDefined": false
      }
    ],
    "isTemplate": false,
    "count": 0,
    "updated": 0
  }
]